<?xml version="1.0" encoding="utf-8"?>
<S:update-report xmlns:S="svn:" xmlns:V="http://subversion.tigris.org/xmlns/dav/" xmlns:D="DAV:"  inline-props="true">
<S:target-revision rev="1049588"/>
<S:open-directory rev="1049587">
<D:checked-in><D:href>/repos/asf/!svn/rvr/1049588/</D:href></D:checked-in>
<S:set-prop name="svn:entry:committed-rev">1049588</S:set-prop>
<S:set-prop name="svn:entry:committed-date">2010-12-15T15:22:27.879725Z</S:set-prop>
<S:set-prop name="svn:entry:last-author">gdusbabek</S:set-prop>
<S:set-prop name="svn:entry:uuid">13f79535-47bb-0310-9956-ffa450edef68</S:set-prop>
<S:open-directory name="cassandra" rev="1049587">
<D:checked-in><D:href>/repos/asf/!svn/rvr/1049588/cassandra</D:href></D:checked-in>
<S:set-prop name="svn:entry:committed-rev">1049588</S:set-prop>
<S:set-prop name="svn:entry:committed-date">2010-12-15T15:22:27.879725Z</S:set-prop>
<S:set-prop name="svn:entry:last-author">gdusbabek</S:set-prop>
<S:set-prop name="svn:entry:uuid">13f79535-47bb-0310-9956-ffa450edef68</S:set-prop>
<S:open-directory name="branches" rev="1049587">
<D:checked-in><D:href>/repos/asf/!svn/rvr/1049588/cassandra/branches</D:href></D:checked-in>
<S:set-prop name="svn:entry:committed-rev">1049588</S:set-prop>
<S:set-prop name="svn:entry:committed-date">2010-12-15T15:22:27.879725Z</S:set-prop>
<S:set-prop name="svn:entry:last-author">gdusbabek</S:set-prop>
<S:set-prop name="svn:entry:uuid">13f79535-47bb-0310-9956-ffa450edef68</S:set-prop>
<S:open-directory name="cassandra-0.7" rev="1049587">
<D:checked-in><D:href>/repos/asf/!svn/rvr/1049588/cassandra/branches/cassandra-0.7</D:href></D:checked-in>
<S:set-prop name="svn:entry:committed-rev">1049588</S:set-prop>
<S:set-prop name="svn:entry:committed-date">2010-12-15T15:22:27.879725Z</S:set-prop>
<S:set-prop name="svn:entry:last-author">gdusbabek</S:set-prop>
<S:set-prop name="svn:entry:uuid">13f79535-47bb-0310-9956-ffa450edef68</S:set-prop>
<S:open-directory name="test" rev="1049587">
<D:checked-in><D:href>/repos/asf/!svn/rvr/1049588/cassandra/branches/cassandra-0.7/test</D:href></D:checked-in>
<S:set-prop name="svn:entry:committed-rev">1049588</S:set-prop>
<S:set-prop name="svn:entry:committed-date">2010-12-15T15:22:27.879725Z</S:set-prop>
<S:set-prop name="svn:entry:last-author">gdusbabek</S:set-prop>
<S:set-prop name="svn:entry:uuid">13f79535-47bb-0310-9956-ffa450edef68</S:set-prop>
<S:open-directory name="unit" rev="1049587">
<D:checked-in><D:href>/repos/asf/!svn/rvr/1049588/cassandra/branches/cassandra-0.7/test/unit</D:href></D:checked-in>
<S:set-prop name="svn:entry:committed-rev">1049588</S:set-prop>
<S:set-prop name="svn:entry:committed-date">2010-12-15T15:22:27.879725Z</S:set-prop>
<S:set-prop name="svn:entry:last-author">gdusbabek</S:set-prop>
<S:set-prop name="svn:entry:uuid">13f79535-47bb-0310-9956-ffa450edef68</S:set-prop>
<S:open-directory name="org" rev="1049587">
<D:checked-in><D:href>/repos/asf/!svn/rvr/1049588/cassandra/branches/cassandra-0.7/test/unit/org</D:href></D:checked-in>
<S:set-prop name="svn:entry:committed-rev">1049588</S:set-prop>
<S:set-prop name="svn:entry:committed-date">2010-12-15T15:22:27.879725Z</S:set-prop>
<S:set-prop name="svn:entry:last-author">gdusbabek</S:set-prop>
<S:set-prop name="svn:entry:uuid">13f79535-47bb-0310-9956-ffa450edef68</S:set-prop>
<S:open-directory name="apache" rev="1049587">
<D:checked-in><D:href>/repos/asf/!svn/rvr/1049588/cassandra/branches/cassandra-0.7/test/unit/org/apache</D:href></D:checked-in>
<S:set-prop name="svn:entry:committed-rev">1049588</S:set-prop>
<S:set-prop name="svn:entry:committed-date">2010-12-15T15:22:27.879725Z</S:set-prop>
<S:set-prop name="svn:entry:last-author">gdusbabek</S:set-prop>
<S:set-prop name="svn:entry:uuid">13f79535-47bb-0310-9956-ffa450edef68</S:set-prop>
<S:open-directory name="cassandra" rev="1049587">
<D:checked-in><D:href>/repos/asf/!svn/rvr/1049588/cassandra/branches/cassandra-0.7/test/unit/org/apache/cassandra</D:href></D:checked-in>
<S:set-prop name="svn:entry:committed-rev">1049588</S:set-prop>
<S:set-prop name="svn:entry:committed-date">2010-12-15T15:22:27.879725Z</S:set-prop>
<S:set-prop name="svn:entry:last-author">gdusbabek</S:set-prop>
<S:set-prop name="svn:entry:uuid">13f79535-47bb-0310-9956-ffa450edef68</S:set-prop>
<S:open-directory name="db" rev="1049587">
<D:checked-in><D:href>/repos/asf/!svn/rvr/1049588/cassandra/branches/cassandra-0.7/test/unit/org/apache/cassandra/db</D:href></D:checked-in>
<S:set-prop name="svn:entry:committed-rev">1049588</S:set-prop>
<S:set-prop name="svn:entry:committed-date">2010-12-15T15:22:27.879725Z</S:set-prop>
<S:set-prop name="svn:entry:last-author">gdusbabek</S:set-prop>
<S:set-prop name="svn:entry:uuid">13f79535-47bb-0310-9956-ffa450edef68</S:set-prop>
<S:open-file name="ColumnFamilyStoreTest.java" rev="1049587">
<D:checked-in><D:href>/repos/asf/!svn/rvr/1049588/cassandra/branches/cassandra-0.7/test/unit/org/apache/cassandra/db/ColumnFamilyStoreTest.java</D:href></D:checked-in>
<S:set-prop name="svn:entry:committed-rev">1049588</S:set-prop>
<S:set-prop name="svn:entry:committed-date">2010-12-15T15:22:27.879725Z</S:set-prop>
<S:set-prop name="svn:entry:last-author">gdusbabek</S:set-prop>
<S:set-prop name="svn:entry:uuid">13f79535-47bb-0310-9956-ffa450edef68</S:set-prop>
<S:fetch-file base-checksum="44e76b2d58947486399ad6b74b663b97" sha1-checksum="f9c8e35263dfaf3ac21df305d82e40a1f0d46d4e"/>
<S:prop><V:md5-checksum>fd53319dc3740012df221f7a4ed79102</V:md5-checksum></S:prop></S:open-file>
</S:open-directory>
</S:open-directory>
</S:open-directory>
</S:open-directory>
</S:open-directory>
</S:open-directory>
<S:open-file name="CHANGES.txt" rev="1049587">
<D:checked-in><D:href>/repos/asf/!svn/rvr/1049588/cassandra/branches/cassandra-0.7/CHANGES.txt</D:href></D:checked-in>
<S:set-prop name="svn:entry:committed-rev">1049588</S:set-prop>
<S:set-prop name="svn:entry:committed-date">2010-12-15T15:22:27.879725Z</S:set-prop>
<S:set-prop name="svn:entry:last-author">gdusbabek</S:set-prop>
<S:set-prop name="svn:entry:uuid">13f79535-47bb-0310-9956-ffa450edef68</S:set-prop>
<S:fetch-file base-checksum="14d6a96a140f166c9c4a3b6014a2392f" sha1-checksum="3ceaeca63ffdfaa3e479b6bea3aaf3610ade85c4"/>
<S:prop><V:md5-checksum>b444a31746902a47125f1d9dd96647dd</V:md5-checksum></S:prop></S:open-file>
<S:open-directory name="src" rev="1049587">
<D:checked-in><D:href>/repos/asf/!svn/rvr/1049588/cassandra/branches/cassandra-0.7/src</D:href></D:checked-in>
<S:set-prop name="svn:entry:committed-rev">1049588</S:set-prop>
<S:set-prop name="svn:entry:committed-date">2010-12-15T15:22:27.879725Z</S:set-prop>
<S:set-prop name="svn:entry:last-author">gdusbabek</S:set-prop>
<S:set-prop name="svn:entry:uuid">13f79535-47bb-0310-9956-ffa450edef68</S:set-prop>
<S:open-directory name="java" rev="1049587">
<D:checked-in><D:href>/repos/asf/!svn/rvr/1049588/cassandra/branches/cassandra-0.7/src/java</D:href></D:checked-in>
<S:set-prop name="svn:entry:committed-rev">1049588</S:set-prop>
<S:set-prop name="svn:entry:committed-date">2010-12-15T15:22:27.879725Z</S:set-prop>
<S:set-prop name="svn:entry:last-author">gdusbabek</S:set-prop>
<S:set-prop name="svn:entry:uuid">13f79535-47bb-0310-9956-ffa450edef68</S:set-prop>
<S:open-directory name="org" rev="1049587">
<D:checked-in><D:href>/repos/asf/!svn/rvr/1049588/cassandra/branches/cassandra-0.7/src/java/org</D:href></D:checked-in>
<S:set-prop name="svn:entry:committed-rev">1049588</S:set-prop>
<S:set-prop name="svn:entry:committed-date">2010-12-15T15:22:27.879725Z</S:set-prop>
<S:set-prop name="svn:entry:last-author">gdusbabek</S:set-prop>
<S:set-prop name="svn:entry:uuid">13f79535-47bb-0310-9956-ffa450edef68</S:set-prop>
<S:open-directory name="apache" rev="1049587">
<D:checked-in><D:href>/repos/asf/!svn/rvr/1049588/cassandra/branches/cassandra-0.7/src/java/org/apache</D:href></D:checked-in>
<S:set-prop name="svn:entry:committed-rev">1049588</S:set-prop>
<S:set-prop name="svn:entry:committed-date">2010-12-15T15:22:27.879725Z</S:set-prop>
<S:set-prop name="svn:entry:last-author">gdusbabek</S:set-prop>
<S:set-prop name="svn:entry:uuid">13f79535-47bb-0310-9956-ffa450edef68</S:set-prop>
<S:open-directory name="cassandra" rev="1049587">
<D:checked-in><D:href>/repos/asf/!svn/rvr/1049588/cassandra/branches/cassandra-0.7/src/java/org/apache/cassandra</D:href></D:checked-in>
<S:set-prop name="svn:entry:committed-rev">1049588</S:set-prop>
<S:set-prop name="svn:entry:committed-date">2010-12-15T15:22:27.879725Z</S:set-prop>
<S:set-prop name="svn:entry:last-author">gdusbabek</S:set-prop>
<S:set-prop name="svn:entry:uuid">13f79535-47bb-0310-9956-ffa450edef68</S:set-prop>
<S:open-directory name="db" rev="1049587">
<D:checked-in><D:href>/repos/asf/!svn/rvr/1049588/cassandra/branches/cassandra-0.7/src/java/org/apache/cassandra/db</D:href></D:checked-in>
<S:set-prop name="svn:entry:committed-rev">1049588</S:set-prop>
<S:set-prop name="svn:entry:committed-date">2010-12-15T15:22:27.879725Z</S:set-prop>
<S:set-prop name="svn:entry:last-author">gdusbabek</S:set-prop>
<S:set-prop name="svn:entry:uuid">13f79535-47bb-0310-9956-ffa450edef68</S:set-prop>
<S:open-file name="RowIteratorFactory.java" rev="1049587">
<D:checked-in><D:href>/repos/asf/!svn/rvr/1049588/cassandra/branches/cassandra-0.7/src/java/org/apache/cassandra/db/RowIteratorFactory.java</D:href></D:checked-in>
<S:set-prop name="svn:entry:committed-rev">1049588</S:set-prop>
<S:set-prop name="svn:entry:committed-date">2010-12-15T15:22:27.879725Z</S:set-prop>
<S:set-prop name="svn:entry:last-author">gdusbabek</S:set-prop>
<S:set-prop name="svn:entry:uuid">13f79535-47bb-0310-9956-ffa450edef68</S:set-prop>
<S:fetch-file base-checksum="1ba87031ee5318465af6b26c1c011f45" sha1-checksum="e1ca83af8b6b61bc8291278a0969cc43347103d3"/>
<S:prop><V:md5-checksum>667ae47945218fa8e4f1ac02c8f2a2e0</V:md5-checksum></S:prop></S:open-file>
<S:open-directory name="columniterator" rev="1049587">
<D:checked-in><D:href>/repos/asf/!svn/rvr/1049588/cassandra/branches/cassandra-0.7/src/java/org/apache/cassandra/db/columniterator</D:href></D:checked-in>
<S:set-prop name="svn:entry:committed-rev">1049588</S:set-prop>
<S:set-prop name="svn:entry:committed-date">2010-12-15T15:22:27.879725Z</S:set-prop>
<S:set-prop name="svn:entry:last-author">gdusbabek</S:set-prop>
<S:set-prop name="svn:entry:uuid">13f79535-47bb-0310-9956-ffa450edef68</S:set-prop>
<S:open-file name="IColumnIterator.java" rev="1049587">
<D:checked-in><D:href>/repos/asf/!svn/rvr/1049588/cassandra/branches/cassandra-0.7/src/java/org/apache/cassandra/db/columniterator/IColumnIterator.java</D:href></D:checked-in>
<S:set-prop name="svn:entry:committed-rev">1049588</S:set-prop>
<S:set-prop name="svn:entry:committed-date">2010-12-15T15:22:27.879725Z</S:set-prop>
<S:set-prop name="svn:entry:last-author">gdusbabek</S:set-prop>
<S:set-prop name="svn:entry:uuid">13f79535-47bb-0310-9956-ffa450edef68</S:set-prop>
<S:fetch-file base-checksum="e6c67a3cfa4f7cecc8ef2120043c39a9" sha1-checksum="905a3a116f4a3723d574d18cdac0e7ac08f384ac"/>
<S:prop><V:md5-checksum>8fad079dcd0b69d10d1004cb9c171d14</V:md5-checksum></S:prop></S:open-file>
</S:open-directory>
</S:open-directory>
</S:open-directory>
</S:open-directory>
</S:open-directory>
</S:open-directory>
</S:open-directory>
</S:open-directory>
</S:open-directory>
</S:open-directory>
</S:open-directory>
</S:update-report>
