<?xml version="1.0" encoding="utf-8"?>
<S:update-report xmlns:S="svn:" xmlns:V="http://subversion.tigris.org/xmlns/dav/" xmlns:D="DAV:"  inline-props="true">
<S:target-revision rev="1369953"/>
<S:open-directory rev="1369952">
<D:checked-in><D:href>/repos/asf/!svn/rvr/1369953/</D:href></D:checked-in>
<S:set-prop name="svn:entry:committed-rev">1369953</S:set-prop>
<S:set-prop name="svn:entry:committed-date">2012-08-06T19:50:37.724379Z</S:set-prop>
<S:set-prop name="svn:entry:last-author">jwross</S:set-prop>
<S:set-prop name="svn:entry:uuid">13f79535-47bb-0310-9956-ffa450edef68</S:set-prop>
<S:open-directory name="aries" rev="1369952">
<D:checked-in><D:href>/repos/asf/!svn/rvr/1369953/aries</D:href></D:checked-in>
<S:set-prop name="svn:entry:committed-rev">1369953</S:set-prop>
<S:set-prop name="svn:entry:committed-date">2012-08-06T19:50:37.724379Z</S:set-prop>
<S:set-prop name="svn:entry:last-author">jwross</S:set-prop>
<S:set-prop name="svn:entry:uuid">13f79535-47bb-0310-9956-ffa450edef68</S:set-prop>
<S:open-directory name="trunk" rev="1369952">
<D:checked-in><D:href>/repos/asf/!svn/rvr/1369953/aries/trunk</D:href></D:checked-in>
<S:set-prop name="svn:entry:committed-rev">1369953</S:set-prop>
<S:set-prop name="svn:entry:committed-date">2012-08-06T19:50:37.724379Z</S:set-prop>
<S:set-prop name="svn:entry:last-author">jwross</S:set-prop>
<S:set-prop name="svn:entry:uuid">13f79535-47bb-0310-9956-ffa450edef68</S:set-prop>
<S:open-directory name="subsystem" rev="1369952">
<D:checked-in><D:href>/repos/asf/!svn/rvr/1369953/aries/trunk/subsystem</D:href></D:checked-in>
<S:set-prop name="svn:entry:committed-rev">1369953</S:set-prop>
<S:set-prop name="svn:entry:committed-date">2012-08-06T19:50:37.724379Z</S:set-prop>
<S:set-prop name="svn:entry:last-author">jwross</S:set-prop>
<S:set-prop name="svn:entry:uuid">13f79535-47bb-0310-9956-ffa450edef68</S:set-prop>
<S:open-directory name="subsystem-core" rev="1369952">
<D:checked-in><D:href>/repos/asf/!svn/rvr/1369953/aries/trunk/subsystem/subsystem-core</D:href></D:checked-in>
<S:set-prop name="svn:entry:committed-rev">1369953</S:set-prop>
<S:set-prop name="svn:entry:committed-date">2012-08-06T19:50:37.724379Z</S:set-prop>
<S:set-prop name="svn:entry:last-author">jwross</S:set-prop>
<S:set-prop name="svn:entry:uuid">13f79535-47bb-0310-9956-ffa450edef68</S:set-prop>
<S:open-directory name="src" rev="1369952">
<D:checked-in><D:href>/repos/asf/!svn/rvr/1369953/aries/trunk/subsystem/subsystem-core/src</D:href></D:checked-in>
<S:set-prop name="svn:entry:committed-rev">1369953</S:set-prop>
<S:set-prop name="svn:entry:committed-date">2012-08-06T19:50:37.724379Z</S:set-prop>
<S:set-prop name="svn:entry:last-author">jwross</S:set-prop>
<S:set-prop name="svn:entry:uuid">13f79535-47bb-0310-9956-ffa450edef68</S:set-prop>
<S:open-directory name="test" rev="1369952">
<D:checked-in><D:href>/repos/asf/!svn/rvr/1369953/aries/trunk/subsystem/subsystem-core/src/test</D:href></D:checked-in>
<S:set-prop name="svn:entry:committed-rev">1369953</S:set-prop>
<S:set-prop name="svn:entry:committed-date">2012-08-06T19:50:37.724379Z</S:set-prop>
<S:set-prop name="svn:entry:last-author">jwross</S:set-prop>
<S:set-prop name="svn:entry:uuid">13f79535-47bb-0310-9956-ffa450edef68</S:set-prop>
<S:open-directory name="java" rev="1369952">
<D:checked-in><D:href>/repos/asf/!svn/rvr/1369953/aries/trunk/subsystem/subsystem-core/src/test/java</D:href></D:checked-in>
<S:set-prop name="svn:entry:committed-rev">1369953</S:set-prop>
<S:set-prop name="svn:entry:committed-date">2012-08-06T19:50:37.724379Z</S:set-prop>
<S:set-prop name="svn:entry:last-author">jwross</S:set-prop>
<S:set-prop name="svn:entry:uuid">13f79535-47bb-0310-9956-ffa450edef68</S:set-prop>
<S:open-directory name="org" rev="1369952">
<D:checked-in><D:href>/repos/asf/!svn/rvr/1369953/aries/trunk/subsystem/subsystem-core/src/test/java/org</D:href></D:checked-in>
<S:set-prop name="svn:entry:committed-rev">1369953</S:set-prop>
<S:set-prop name="svn:entry:committed-date">2012-08-06T19:50:37.724379Z</S:set-prop>
<S:set-prop name="svn:entry:last-author">jwross</S:set-prop>
<S:set-prop name="svn:entry:uuid">13f79535-47bb-0310-9956-ffa450edef68</S:set-prop>
<S:open-directory name="apache" rev="1369952">
<D:checked-in><D:href>/repos/asf/!svn/rvr/1369953/aries/trunk/subsystem/subsystem-core/src/test/java/org/apache</D:href></D:checked-in>
<S:set-prop name="svn:entry:committed-rev">1369953</S:set-prop>
<S:set-prop name="svn:entry:committed-date">2012-08-06T19:50:37.724379Z</S:set-prop>
<S:set-prop name="svn:entry:last-author">jwross</S:set-prop>
<S:set-prop name="svn:entry:uuid">13f79535-47bb-0310-9956-ffa450edef68</S:set-prop>
<S:open-directory name="aries" rev="1369952">
<D:checked-in><D:href>/repos/asf/!svn/rvr/1369953/aries/trunk/subsystem/subsystem-core/src/test/java/org/apache/aries</D:href></D:checked-in>
<S:set-prop name="svn:entry:committed-rev">1369953</S:set-prop>
<S:set-prop name="svn:entry:committed-date">2012-08-06T19:50:37.724379Z</S:set-prop>
<S:set-prop name="svn:entry:last-author">jwross</S:set-prop>
<S:set-prop name="svn:entry:uuid">13f79535-47bb-0310-9956-ffa450edef68</S:set-prop>
<S:open-directory name="subsystem" rev="1369952">
<D:checked-in><D:href>/repos/asf/!svn/rvr/1369953/aries/trunk/subsystem/subsystem-core/src/test/java/org/apache/aries/subsystem</D:href></D:checked-in>
<S:set-prop name="svn:entry:committed-rev">1369953</S:set-prop>
<S:set-prop name="svn:entry:committed-date">2012-08-06T19:50:37.724379Z</S:set-prop>
<S:set-prop name="svn:entry:last-author">jwross</S:set-prop>
<S:set-prop name="svn:entry:uuid">13f79535-47bb-0310-9956-ffa450edef68</S:set-prop>
<S:open-directory name="core" rev="1369952">
<D:checked-in><D:href>/repos/asf/!svn/rvr/1369953/aries/trunk/subsystem/subsystem-core/src/test/java/org/apache/aries/subsystem/core</D:href></D:checked-in>
<S:set-prop name="svn:entry:committed-rev">1369953</S:set-prop>
<S:set-prop name="svn:entry:committed-date">2012-08-06T19:50:37.724379Z</S:set-prop>
<S:set-prop name="svn:entry:last-author">jwross</S:set-prop>
<S:set-prop name="svn:entry:uuid">13f79535-47bb-0310-9956-ffa450edef68</S:set-prop>
<S:delete-entry name="Temp.java" rev="1369953"/>
<S:add-directory name="archive" bc-url="/repos/asf/!svn/bc/1369953/aries/trunk/subsystem/subsystem-core/src/test/java/org/apache/aries/subsystem/core/archive">
<D:checked-in><D:href>/repos/asf/!svn/rvr/1369953/aries/trunk/subsystem/subsystem-core/src/test/java/org/apache/aries/subsystem/core/archive</D:href></D:checked-in>
<S:set-prop name="svn:entry:committed-rev">1369953</S:set-prop>
<S:set-prop name="svn:entry:committed-date">2012-08-06T19:50:37.724379Z</S:set-prop>
<S:set-prop name="svn:entry:last-author">jwross</S:set-prop>
<S:set-prop name="svn:entry:uuid">13f79535-47bb-0310-9956-ffa450edef68</S:set-prop>
<S:add-file name="ImportPackageHeaderTest.java" sha1-checksum="aaa68bafdaff8be09fa7044bc03274720968098d">
<D:checked-in><D:href>/repos/asf/!svn/rvr/1369953/aries/trunk/subsystem/subsystem-core/src/test/java/org/apache/aries/subsystem/core/archive/ImportPackageHeaderTest.java</D:href></D:checked-in>
<S:set-prop name="svn:entry:committed-rev">1369953</S:set-prop>
<S:set-prop name="svn:entry:committed-date">2012-08-06T19:50:37.724379Z</S:set-prop>
<S:set-prop name="svn:entry:last-author">jwross</S:set-prop>
<S:set-prop name="svn:entry:uuid">13f79535-47bb-0310-9956-ffa450edef68</S:set-prop>
<S:prop><V:md5-checksum>23dae62bf09c931c524977be6e6be2f4</V:md5-checksum></S:prop></S:add-file>
</S:add-directory>
</S:open-directory>
</S:open-directory>
</S:open-directory>
</S:open-directory>
</S:open-directory>
</S:open-directory>
</S:open-directory>
<S:open-directory name="main" rev="1369952">
<D:checked-in><D:href>/repos/asf/!svn/rvr/1369953/aries/trunk/subsystem/subsystem-core/src/main</D:href></D:checked-in>
<S:set-prop name="svn:entry:committed-rev">1369953</S:set-prop>
<S:set-prop name="svn:entry:committed-date">2012-08-06T19:50:37.724379Z</S:set-prop>
<S:set-prop name="svn:entry:last-author">jwross</S:set-prop>
<S:set-prop name="svn:entry:uuid">13f79535-47bb-0310-9956-ffa450edef68</S:set-prop>
<S:open-directory name="java" rev="1369952">
<D:checked-in><D:href>/repos/asf/!svn/rvr/1369953/aries/trunk/subsystem/subsystem-core/src/main/java</D:href></D:checked-in>
<S:set-prop name="svn:entry:committed-rev">1369953</S:set-prop>
<S:set-prop name="svn:entry:committed-date">2012-08-06T19:50:37.724379Z</S:set-prop>
<S:set-prop name="svn:entry:last-author">jwross</S:set-prop>
<S:set-prop name="svn:entry:uuid">13f79535-47bb-0310-9956-ffa450edef68</S:set-prop>
<S:open-directory name="org" rev="1369952">
<D:checked-in><D:href>/repos/asf/!svn/rvr/1369953/aries/trunk/subsystem/subsystem-core/src/main/java/org</D:href></D:checked-in>
<S:set-prop name="svn:entry:committed-rev">1369953</S:set-prop>
<S:set-prop name="svn:entry:committed-date">2012-08-06T19:50:37.724379Z</S:set-prop>
<S:set-prop name="svn:entry:last-author">jwross</S:set-prop>
<S:set-prop name="svn:entry:uuid">13f79535-47bb-0310-9956-ffa450edef68</S:set-prop>
<S:open-directory name="apache" rev="1369952">
<D:checked-in><D:href>/repos/asf/!svn/rvr/1369953/aries/trunk/subsystem/subsystem-core/src/main/java/org/apache</D:href></D:checked-in>
<S:set-prop name="svn:entry:committed-rev">1369953</S:set-prop>
<S:set-prop name="svn:entry:committed-date">2012-08-06T19:50:37.724379Z</S:set-prop>
<S:set-prop name="svn:entry:last-author">jwross</S:set-prop>
<S:set-prop name="svn:entry:uuid">13f79535-47bb-0310-9956-ffa450edef68</S:set-prop>
<S:open-directory name="aries" rev="1369952">
<D:checked-in><D:href>/repos/asf/!svn/rvr/1369953/aries/trunk/subsystem/subsystem-core/src/main/java/org/apache/aries</D:href></D:checked-in>
<S:set-prop name="svn:entry:committed-rev">1369953</S:set-prop>
<S:set-prop name="svn:entry:committed-date">2012-08-06T19:50:37.724379Z</S:set-prop>
<S:set-prop name="svn:entry:last-author">jwross</S:set-prop>
<S:set-prop name="svn:entry:uuid">13f79535-47bb-0310-9956-ffa450edef68</S:set-prop>
<S:open-directory name="subsystem" rev="1369952">
<D:checked-in><D:href>/repos/asf/!svn/rvr/1369953/aries/trunk/subsystem/subsystem-core/src/main/java/org/apache/aries/subsystem</D:href></D:checked-in>
<S:set-prop name="svn:entry:committed-rev">1369953</S:set-prop>
<S:set-prop name="svn:entry:committed-date">2012-08-06T19:50:37.724379Z</S:set-prop>
<S:set-prop name="svn:entry:last-author">jwross</S:set-prop>
<S:set-prop name="svn:entry:uuid">13f79535-47bb-0310-9956-ffa450edef68</S:set-prop>
<S:open-directory name="core" rev="1369952">
<D:checked-in><D:href>/repos/asf/!svn/rvr/1369953/aries/trunk/subsystem/subsystem-core/src/main/java/org/apache/aries/subsystem/core</D:href></D:checked-in>
<S:set-prop name="svn:entry:committed-rev">1369953</S:set-prop>
<S:set-prop name="svn:entry:committed-date">2012-08-06T19:50:37.724379Z</S:set-prop>
<S:set-prop name="svn:entry:last-author">jwross</S:set-prop>
<S:set-prop name="svn:entry:uuid">13f79535-47bb-0310-9956-ffa450edef68</S:set-prop>
<S:open-directory name="internal" rev="1369952">
<D:checked-in><D:href>/repos/asf/!svn/rvr/1369953/aries/trunk/subsystem/subsystem-core/src/main/java/org/apache/aries/subsystem/core/internal</D:href></D:checked-in>
<S:set-prop name="svn:entry:committed-rev">1369953</S:set-prop>
<S:set-prop name="svn:entry:committed-date">2012-08-06T19:50:37.724379Z</S:set-prop>
<S:set-prop name="svn:entry:last-author">jwross</S:set-prop>
<S:set-prop name="svn:entry:uuid">13f79535-47bb-0310-9956-ffa450edef68</S:set-prop>
<S:open-file name="SubsystemResource.java" rev="1369952">
<D:checked-in><D:href>/repos/asf/!svn/rvr/1369953/aries/trunk/subsystem/subsystem-core/src/main/java/org/apache/aries/subsystem/core/internal/SubsystemResource.java</D:href></D:checked-in>
<S:set-prop name="svn:entry:committed-rev">1369953</S:set-prop>
<S:set-prop name="svn:entry:committed-date">2012-08-06T19:50:37.724379Z</S:set-prop>
<S:set-prop name="svn:entry:last-author">jwross</S:set-prop>
<S:set-prop name="svn:entry:uuid">13f79535-47bb-0310-9956-ffa450edef68</S:set-prop>
<S:fetch-file base-checksum="67ceb9f5ddbf8b43ca0542fbc98adc63" sha1-checksum="17740336c6df32402e140f4f5873c37c3d441198"/>
<S:prop><V:md5-checksum>60895010f2cd7535cebf391f3ee30766</V:md5-checksum></S:prop></S:open-file>
</S:open-directory>
<S:open-directory name="archive" rev="1369952">
<D:checked-in><D:href>/repos/asf/!svn/rvr/1369953/aries/trunk/subsystem/subsystem-core/src/main/java/org/apache/aries/subsystem/core/archive</D:href></D:checked-in>
<S:set-prop name="svn:entry:committed-rev">1369953</S:set-prop>
<S:set-prop name="svn:entry:committed-date">2012-08-06T19:50:37.724379Z</S:set-prop>
<S:set-prop name="svn:entry:last-author">jwross</S:set-prop>
<S:set-prop name="svn:entry:uuid">13f79535-47bb-0310-9956-ffa450edef68</S:set-prop>
<S:open-file name="ImportPackageHeader.java" rev="1369952">
<D:checked-in><D:href>/repos/asf/!svn/rvr/1369953/aries/trunk/subsystem/subsystem-core/src/main/java/org/apache/aries/subsystem/core/archive/ImportPackageHeader.java</D:href></D:checked-in>
<S:set-prop name="svn:entry:committed-rev">1369953</S:set-prop>
<S:set-prop name="svn:entry:committed-date">2012-08-06T19:50:37.724379Z</S:set-prop>
<S:set-prop name="svn:entry:last-author">jwross</S:set-prop>
<S:set-prop name="svn:entry:uuid">13f79535-47bb-0310-9956-ffa450edef68</S:set-prop>
<S:fetch-file base-checksum="1d8620692feb42efacf04ad179aee0dd" sha1-checksum="ec2b5a26566fbd9050ebe454eb4afded9931ab0d"/>
<S:prop><V:md5-checksum>372f48e8bbc2e2bf5be9e52add4b19b6</V:md5-checksum></S:prop></S:open-file>
</S:open-directory>
</S:open-directory>
</S:open-directory>
</S:open-directory>
</S:open-directory>
</S:open-directory>
</S:open-directory>
</S:open-directory>
</S:open-directory>
</S:open-directory>
</S:open-directory>
</S:open-directory>
</S:open-directory>
</S:open-directory>
</S:update-report>
