<?xml version="1.0" encoding="utf-8"?>
<S:update-report xmlns:S="svn:" xmlns:V="http://subversion.tigris.org/xmlns/dav/" xmlns:D="DAV:"  inline-props="true">
<S:target-revision rev="607521"/>
<S:open-directory rev="607520">
<D:checked-in><D:href>/repos/asf/!svn/rvr/607521/</D:href></D:checked-in>
<S:set-prop name="svn:entry:committed-rev">607521</S:set-prop>
<S:set-prop name="svn:entry:committed-date">2007-12-30T07:34:30.858936Z</S:set-prop>
<S:set-prop name="svn:entry:last-author">doronc</S:set-prop>
<S:set-prop name="svn:entry:uuid">13f79535-47bb-0310-9956-ffa450edef68</S:set-prop>
<S:open-directory name="lucene" rev="607520">
<D:checked-in><D:href>/repos/asf/!svn/rvr/607521/lucene</D:href></D:checked-in>
<S:set-prop name="svn:entry:committed-rev">607521</S:set-prop>
<S:set-prop name="svn:entry:committed-date">2007-12-30T07:34:30.858936Z</S:set-prop>
<S:set-prop name="svn:entry:last-author">doronc</S:set-prop>
<S:set-prop name="svn:entry:uuid">13f79535-47bb-0310-9956-ffa450edef68</S:set-prop>
<S:open-directory name="java" rev="607520">
<D:checked-in><D:href>/repos/asf/!svn/rvr/607521/lucene/java</D:href></D:checked-in>
<S:set-prop name="svn:entry:committed-rev">607521</S:set-prop>
<S:set-prop name="svn:entry:committed-date">2007-12-30T07:34:30.858936Z</S:set-prop>
<S:set-prop name="svn:entry:last-author">doronc</S:set-prop>
<S:set-prop name="svn:entry:uuid">13f79535-47bb-0310-9956-ffa450edef68</S:set-prop>
<S:open-directory name="trunk" rev="607520">
<D:checked-in><D:href>/repos/asf/!svn/rvr/607521/lucene/java/trunk</D:href></D:checked-in>
<S:set-prop name="svn:entry:committed-rev">607521</S:set-prop>
<S:set-prop name="svn:entry:committed-date">2007-12-30T07:34:30.858936Z</S:set-prop>
<S:set-prop name="svn:entry:last-author">doronc</S:set-prop>
<S:set-prop name="svn:entry:uuid">13f79535-47bb-0310-9956-ffa450edef68</S:set-prop>
<S:open-file name="CHANGES.txt" rev="607520">
<D:checked-in><D:href>/repos/asf/!svn/rvr/607521/lucene/java/trunk/CHANGES.txt</D:href></D:checked-in>
<S:set-prop name="svn:entry:committed-rev">607521</S:set-prop>
<S:set-prop name="svn:entry:committed-date">2007-12-30T07:34:30.858936Z</S:set-prop>
<S:set-prop name="svn:entry:last-author">doronc</S:set-prop>
<S:set-prop name="svn:entry:uuid">13f79535-47bb-0310-9956-ffa450edef68</S:set-prop>
<S:fetch-file base-checksum="bd14c554a9825958f609705dc9358891" sha1-checksum="2019f076df8ea7704475a50b2780a8014107b292"/>
<S:prop><V:md5-checksum>988656ae1a540b7767d6aa542cefd0a0</V:md5-checksum></S:prop></S:open-file>
<S:open-directory name="src" rev="607520">
<D:checked-in><D:href>/repos/asf/!svn/rvr/607521/lucene/java/trunk/src</D:href></D:checked-in>
<S:set-prop name="svn:entry:committed-rev">607521</S:set-prop>
<S:set-prop name="svn:entry:committed-date">2007-12-30T07:34:30.858936Z</S:set-prop>
<S:set-prop name="svn:entry:last-author">doronc</S:set-prop>
<S:set-prop name="svn:entry:uuid">13f79535-47bb-0310-9956-ffa450edef68</S:set-prop>
<S:open-directory name="java" rev="607520">
<D:checked-in><D:href>/repos/asf/!svn/rvr/607521/lucene/java/trunk/src/java</D:href></D:checked-in>
<S:set-prop name="svn:entry:committed-rev">607521</S:set-prop>
<S:set-prop name="svn:entry:committed-date">2007-12-30T07:34:30.858936Z</S:set-prop>
<S:set-prop name="svn:entry:last-author">doronc</S:set-prop>
<S:set-prop name="svn:entry:uuid">13f79535-47bb-0310-9956-ffa450edef68</S:set-prop>
<S:open-directory name="org" rev="607520">
<D:checked-in><D:href>/repos/asf/!svn/rvr/607521/lucene/java/trunk/src/java/org</D:href></D:checked-in>
<S:set-prop name="svn:entry:committed-rev">607521</S:set-prop>
<S:set-prop name="svn:entry:committed-date">2007-12-30T07:34:30.858936Z</S:set-prop>
<S:set-prop name="svn:entry:last-author">doronc</S:set-prop>
<S:set-prop name="svn:entry:uuid">13f79535-47bb-0310-9956-ffa450edef68</S:set-prop>
<S:open-directory name="apache" rev="607520">
<D:checked-in><D:href>/repos/asf/!svn/rvr/607521/lucene/java/trunk/src/java/org/apache</D:href></D:checked-in>
<S:set-prop name="svn:entry:committed-rev">607521</S:set-prop>
<S:set-prop name="svn:entry:committed-date">2007-12-30T07:34:30.858936Z</S:set-prop>
<S:set-prop name="svn:entry:last-author">doronc</S:set-prop>
<S:set-prop name="svn:entry:uuid">13f79535-47bb-0310-9956-ffa450edef68</S:set-prop>
<S:open-directory name="lucene" rev="607520">
<D:checked-in><D:href>/repos/asf/!svn/rvr/607521/lucene/java/trunk/src/java/org/apache/lucene</D:href></D:checked-in>
<S:set-prop name="svn:entry:committed-rev">607521</S:set-prop>
<S:set-prop name="svn:entry:committed-date">2007-12-30T07:34:30.858936Z</S:set-prop>
<S:set-prop name="svn:entry:last-author">doronc</S:set-prop>
<S:set-prop name="svn:entry:uuid">13f79535-47bb-0310-9956-ffa450edef68</S:set-prop>
<S:open-directory name="analysis" rev="607520">
<D:checked-in><D:href>/repos/asf/!svn/rvr/607521/lucene/java/trunk/src/java/org/apache/lucene/analysis</D:href></D:checked-in>
<S:set-prop name="svn:entry:committed-rev">607521</S:set-prop>
<S:set-prop name="svn:entry:committed-date">2007-12-30T07:34:30.858936Z</S:set-prop>
<S:set-prop name="svn:entry:last-author">doronc</S:set-prop>
<S:set-prop name="svn:entry:uuid">13f79535-47bb-0310-9956-ffa450edef68</S:set-prop>
<S:open-file name="TokenStream.java" rev="607520">
<D:checked-in><D:href>/repos/asf/!svn/rvr/607521/lucene/java/trunk/src/java/org/apache/lucene/analysis/TokenStream.java</D:href></D:checked-in>
<S:set-prop name="svn:entry:committed-rev">607521</S:set-prop>
<S:set-prop name="svn:entry:committed-date">2007-12-30T07:34:30.858936Z</S:set-prop>
<S:set-prop name="svn:entry:last-author">doronc</S:set-prop>
<S:set-prop name="svn:entry:uuid">13f79535-47bb-0310-9956-ffa450edef68</S:set-prop>
<S:fetch-file base-checksum="1288551999a3b8c2ba6d9250625ae3e9" sha1-checksum="d32fce6aa758e81509e780d255bb1f19f81e8b9b"/>
<S:prop><V:md5-checksum>a81bcc4563a91211983e7418ca56988b</V:md5-checksum></S:prop></S:open-file>
<S:open-file name="CharTokenizer.java" rev="607520">
<D:checked-in><D:href>/repos/asf/!svn/rvr/607521/lucene/java/trunk/src/java/org/apache/lucene/analysis/CharTokenizer.java</D:href></D:checked-in>
<S:set-prop name="svn:entry:committed-rev">607521</S:set-prop>
<S:set-prop name="svn:entry:committed-date">2007-12-30T07:34:30.858936Z</S:set-prop>
<S:set-prop name="svn:entry:last-author">doronc</S:set-prop>
<S:set-prop name="svn:entry:uuid">13f79535-47bb-0310-9956-ffa450edef68</S:set-prop>
<S:fetch-file base-checksum="4e5ecc6f15688d4e1ad21129937a4b34" sha1-checksum="e013133234861ab64b8b1c3f1b6a8dfa93affd6c"/>
<S:prop><V:md5-checksum>148d5b9f20cb4d47cb8ddb88a83b2bbb</V:md5-checksum></S:prop></S:open-file>
<S:open-file name="Tokenizer.java" rev="607520">
<D:checked-in><D:href>/repos/asf/!svn/rvr/607521/lucene/java/trunk/src/java/org/apache/lucene/analysis/Tokenizer.java</D:href></D:checked-in>
<S:set-prop name="svn:entry:committed-rev">607521</S:set-prop>
<S:set-prop name="svn:entry:committed-date">2007-12-30T07:34:30.858936Z</S:set-prop>
<S:set-prop name="svn:entry:last-author">doronc</S:set-prop>
<S:set-prop name="svn:entry:uuid">13f79535-47bb-0310-9956-ffa450edef68</S:set-prop>
<S:fetch-file base-checksum="891f1f2ed4c0872da02074bb502a8ea3" sha1-checksum="557bc3bf61d5c320fb8f0f865e065b816a17ee34"/>
<S:prop><V:md5-checksum>2aaef58b399a10b293e33bf785e772d3</V:md5-checksum></S:prop></S:open-file>
<S:open-file name="KeywordTokenizer.java" rev="607520">
<D:checked-in><D:href>/repos/asf/!svn/rvr/607521/lucene/java/trunk/src/java/org/apache/lucene/analysis/KeywordTokenizer.java</D:href></D:checked-in>
<S:set-prop name="svn:entry:committed-rev">607521</S:set-prop>
<S:set-prop name="svn:entry:committed-date">2007-12-30T07:34:30.858936Z</S:set-prop>
<S:set-prop name="svn:entry:last-author">doronc</S:set-prop>
<S:set-prop name="svn:entry:uuid">13f79535-47bb-0310-9956-ffa450edef68</S:set-prop>
<S:fetch-file base-checksum="09692771fef39ca9ba9a87f64d94ad5e" sha1-checksum="af3dc69492cef5afe9dcad2d3f2a5511a9749ed7"/>
<S:prop><V:md5-checksum>f937c2ed3c7b0eb55de6ffdd454180a9</V:md5-checksum></S:prop></S:open-file>
<S:open-directory name="standard" rev="607520">
<D:checked-in><D:href>/repos/asf/!svn/rvr/607521/lucene/java/trunk/src/java/org/apache/lucene/analysis/standard</D:href></D:checked-in>
<S:set-prop name="svn:entry:committed-rev">607521</S:set-prop>
<S:set-prop name="svn:entry:committed-date">2007-12-30T07:34:30.858936Z</S:set-prop>
<S:set-prop name="svn:entry:last-author">doronc</S:set-prop>
<S:set-prop name="svn:entry:uuid">13f79535-47bb-0310-9956-ffa450edef68</S:set-prop>
<S:open-file name="StandardTokenizer.java" rev="607520">
<D:checked-in><D:href>/repos/asf/!svn/rvr/607521/lucene/java/trunk/src/java/org/apache/lucene/analysis/standard/StandardTokenizer.java</D:href></D:checked-in>
<S:set-prop name="svn:entry:committed-rev">607521</S:set-prop>
<S:set-prop name="svn:entry:committed-date">2007-12-30T07:34:30.858936Z</S:set-prop>
<S:set-prop name="svn:entry:last-author">doronc</S:set-prop>
<S:set-prop name="svn:entry:uuid">13f79535-47bb-0310-9956-ffa450edef68</S:set-prop>
<S:fetch-file base-checksum="c2dd4841614f138ad24202154865a300" sha1-checksum="9f6ed7acb8c1d4e7094aeb81fa2cee381f2c2fa2"/>
<S:prop><V:md5-checksum>bfe28cd4e3ec367f23978e94800f1e2e</V:md5-checksum></S:prop></S:open-file>
</S:open-directory>
</S:open-directory>
<S:open-directory name="index" rev="607520">
<D:checked-in><D:href>/repos/asf/!svn/rvr/607521/lucene/java/trunk/src/java/org/apache/lucene/index</D:href></D:checked-in>
<S:set-prop name="svn:entry:committed-rev">607521</S:set-prop>
<S:set-prop name="svn:entry:committed-date">2007-12-30T07:34:30.858936Z</S:set-prop>
<S:set-prop name="svn:entry:last-author">doronc</S:set-prop>
<S:set-prop name="svn:entry:uuid">13f79535-47bb-0310-9956-ffa450edef68</S:set-prop>
<S:open-file name="DocumentsWriter.java" rev="607520">
<D:checked-in><D:href>/repos/asf/!svn/rvr/607521/lucene/java/trunk/src/java/org/apache/lucene/index/DocumentsWriter.java</D:href></D:checked-in>
<S:set-prop name="svn:entry:committed-rev">607521</S:set-prop>
<S:set-prop name="svn:entry:committed-date">2007-12-30T07:34:30.858936Z</S:set-prop>
<S:set-prop name="svn:entry:last-author">doronc</S:set-prop>
<S:set-prop name="svn:entry:uuid">13f79535-47bb-0310-9956-ffa450edef68</S:set-prop>
<S:fetch-file base-checksum="3ffac302216d3f0a4f2e8cdc72991838" sha1-checksum="704a417b0beee1218ec33923ecf968cf505d664d"/>
<S:prop><V:md5-checksum>ca3fd56f0ff519d2b0d5c079c02240af</V:md5-checksum></S:prop></S:open-file>
</S:open-directory>
</S:open-directory>
</S:open-directory>
</S:open-directory>
</S:open-directory>
</S:open-directory>
</S:open-directory>
</S:open-directory>
</S:open-directory>
</S:open-directory>
</S:update-report>
