{"expand":"renderedFields,names,schema,transitions,operations,editmeta,changelog","id":"12413107","self":"https://issues.apache.org/jira/rest/api/latest/issue/12413107","key":"LUCENE-1527","fields":{"issuetype":{"self":"https://issues.apache.org/jira/rest/api/2/issuetype/1","id":"1","description":"A problem which impairs or prevents the functions of the product.","iconUrl":"https://issues.apache.org/jira/images/icons/issuetypes/bug.png","name":"Bug","subtask":false},"timespent":null,"project":{"self":"https://issues.apache.org/jira/rest/api/2/project/12310110","id":"12310110","key":"LUCENE","name":"Lucene - Core","avatarUrls":{"48x48":"https://issues.apache.org/jira/secure/projectavatar?pid=12310110&avatarId=10061","24x24":"https://issues.apache.org/jira/secure/projectavatar?size=small&pid=12310110&avatarId=10061","16x16":"https://issues.apache.org/jira/secure/projectavatar?size=xsmall&pid=12310110&avatarId=10061","32x32":"https://issues.apache.org/jira/secure/projectavatar?size=medium&pid=12310110&avatarId=10061"},"projectCategory":{"self":"https://issues.apache.org/jira/rest/api/2/projectCategory/10150","id":"10150","description":"Lucene-related projects","name":"Lucene"}},"fixVersions":[{"self":"https://issues.apache.org/jira/rest/api/2/version/12312682","id":"12312682","description":"Last release (barring major bugs) before migrating to 3.0 and JDK 1.5","name":"2.9","archived":false,"released":true,"releaseDate":"2009-09-25"}],"aggregatetimespent":null,"resolution":{"self":"https://issues.apache.org/jira/rest/api/2/resolution/1","id":"1","description":"A fix for this issue is checked into the tree and tested.","name":"Fixed"},"customfield_12312322":null,"customfield_12310220":"2009-01-23 20:34:03.007","customfield_12312323":null,"customfield_12310420":"12226","customfield_12312320":null,"customfield_12310222":"1_*:*_1_*:*_13953009_*|*_5_*:*_1_*:*_0","customfield_12312321":null,"customfield_12312120":null,"customfield_12312121":null,"resolutiondate":"2009-01-23T20:34:03.009+0000","workratio":0,"customfield_12312328":null,"customfield_12312329":null,"customfield_12312326":null,"customfield_12310300":null,"customfield_12312327":null,"customfield_12312324":null,"customfield_12312325":null,"lastViewed":null,"watches":{"self":"https://issues.apache.org/jira/rest/api/2/issue/LUCENE-1527/watchers","watchCount":1,"isWatching":false},"created":"2009-01-23T16:41:30.390+0000","priority":{"self":"https://issues.apache.org/jira/rest/api/2/priority/5","iconUrl":"https://issues.apache.org/jira/images/icons/priorities/trivial.png","name":"Trivial","id":"5"},"labels":[],"customfield_12312333":null,"customfield_12312334":null,"customfield_12310310":"1.0","customfield_12312331":null,"customfield_12312332":null,"timeestimate":3600,"aggregatetimeoriginalestimate":3600,"customfield_12312330":null,"customfield_12311120":null,"versions":[{"self":"https://issues.apache.org/jira/rest/api/2/version/12312681","id":"12312681","description":"","name":"2.4","archived":false,"released":true,"releaseDate":"2008-10-08"}],"issuelinks":[],"customfield_12312339":null,"assignee":{"self":"https://issues.apache.org/jira/rest/api/2/user?username=mikemccand","name":"mikemccand","emailAddress":"lucene at mikemccandless dot com","avatarUrls":{"48x48":"https://issues.apache.org/jira/secure/useravatar?avatarId=10452","24x24":"https://issues.apache.org/jira/secure/useravatar?size=small&avatarId=10452","16x16":"https://issues.apache.org/jira/secure/useravatar?size=xsmall&avatarId=10452","32x32":"https://issues.apache.org/jira/secure/useravatar?size=medium&avatarId=10452"},"displayName":"Michael McCandless","active":true},"customfield_12312337":null,"customfield_12312338":null,"updated":"2009-09-25T16:23:17.901+0000","customfield_12312335":null,"customfield_12312336":null,"customfield_12311720":null,"status":{"self":"https://issues.apache.org/jira/rest/api/2/status/6","description":"The issue is considered finished, the resolution is correct. Issues which are closed can be reopened.","iconUrl":"https://issues.apache.org/jira/images/icons/statuses/closed.png","name":"Closed","id":"6","statusCategory":{"self":"https://issues.apache.org/jira/rest/api/2/statuscategory/3","id":3,"key":"done","colorName":"green","name":"Complete"}},"components":[{"self":"https://issues.apache.org/jira/rest/api/2/component/12311676","id":"12311676","name":"modules/benchmark","description":"issues related to the benchmarking module"}],"timeoriginalestimate":3600,"description":"Benchmark deletes.alg fails because the index reader defaults to open readonly.  ","customfield_10010":null,"timetracking":{"originalEstimate":"1h","remainingEstimate":"1h","originalEstimateSeconds":3600,"remainingEstimateSeconds":3600},"customfield_12310120":[{"self":"https://issues.apache.org/jira/rest/api/2/customFieldOption/10121","value":"New","id":"10121"}],"customfield_12312026":null,"customfield_12312023":null,"customfield_12312024":null,"customfield_12312340":null,"aggregatetimeestimate":3600,"customfield_12312022":null,"customfield_12312341":null,"customfield_12312220":null,"customfield_12310921":null,"customfield_12310920":"26520","summary":"Benchmark deletes.alg fails","creator":{"self":"https://issues.apache.org/jira/rest/api/2/user?username=jasonrutherglen","name":"jasonrutherglen","emailAddress":"jason dot rutherglen at gmail dot com","avatarUrls":{"48x48":"https://issues.apache.org/jira/secure/useravatar?avatarId=10452","24x24":"https://issues.apache.org/jira/secure/useravatar?size=small&avatarId=10452","16x16":"https://issues.apache.org/jira/secure/useravatar?size=xsmall&avatarId=10452","32x32":"https://issues.apache.org/jira/secure/useravatar?size=medium&avatarId=10452"},"displayName":"Jason Rutherglen","active":true},"subtasks":[],"customfield_12310291":null,"reporter":{"self":"https://issues.apache.org/jira/rest/api/2/user?username=jasonrutherglen","name":"jasonrutherglen","emailAddress":"jason dot rutherglen at gmail dot com","avatarUrls":{"48x48":"https://issues.apache.org/jira/secure/useravatar?avatarId=10452","24x24":"https://issues.apache.org/jira/secure/useravatar?size=small&avatarId=10452","16x16":"https://issues.apache.org/jira/secure/useravatar?size=xsmall&avatarId=10452","32x32":"https://issues.apache.org/jira/secure/useravatar?size=medium&avatarId=10452"},"displayName":"Jason Rutherglen","active":true},"customfield_12310290":null,"aggregateprogress":{"progress":0,"total":3600,"percent":0},"customfield_12311024":null,"environment":null,"customfield_12311020":null,"duedate":null,"customfield_12310250":null,"progress":{"progress":0,"total":3600,"percent":0},"comment":{"startAt":0,"maxResults":2,"total":2,"comments":[{"self":"https://issues.apache.org/jira/rest/api/2/issue/12413107/comment/12666595","id":"12666595","author":{"self":"https://issues.apache.org/jira/rest/api/2/user?username=jasonrutherglen","name":"jasonrutherglen","emailAddress":"jason dot rutherglen at gmail dot com","avatarUrls":{"48x48":"https://issues.apache.org/jira/secure/useravatar?avatarId=10452","24x24":"https://issues.apache.org/jira/secure/useravatar?size=small&avatarId=10452","16x16":"https://issues.apache.org/jira/secure/useravatar?size=xsmall&avatarId=10452","32x32":"https://issues.apache.org/jira/secure/useravatar?size=medium&avatarId=10452"},"displayName":"Jason Rutherglen","active":true},"body":"Adds false parameter to OpenReader in deletes.alg","updateAuthor":{"self":"https://issues.apache.org/jira/rest/api/2/user?username=jasonrutherglen","name":"jasonrutherglen","emailAddress":"jason dot rutherglen at gmail dot com","avatarUrls":{"48x48":"https://issues.apache.org/jira/secure/useravatar?avatarId=10452","24x24":"https://issues.apache.org/jira/secure/useravatar?size=small&avatarId=10452","16x16":"https://issues.apache.org/jira/secure/useravatar?size=xsmall&avatarId=10452","32x32":"https://issues.apache.org/jira/secure/useravatar?size=medium&avatarId=10452"},"displayName":"Jason Rutherglen","active":true},"created":"2009-01-23T16:44:57.605+0000","updated":"2009-01-23T16:45:48.268+0000"},{"self":"https://issues.apache.org/jira/rest/api/2/issue/12413107/comment/12666691","id":"12666691","author":{"self":"https://issues.apache.org/jira/rest/api/2/user?username=mikemccand","name":"mikemccand","emailAddress":"lucene at mikemccandless dot com","avatarUrls":{"48x48":"https://issues.apache.org/jira/secure/useravatar?avatarId=10452","24x24":"https://issues.apache.org/jira/secure/useravatar?size=small&avatarId=10452","16x16":"https://issues.apache.org/jira/secure/useravatar?size=xsmall&avatarId=10452","32x32":"https://issues.apache.org/jira/secure/useravatar?size=medium&avatarId=10452"},"displayName":"Michael McCandless","active":true},"body":"Committed revision 737175.  Thanks Jason!","updateAuthor":{"self":"https://issues.apache.org/jira/rest/api/2/user?username=mikemccand","name":"mikemccand","emailAddress":"lucene at mikemccandless dot com","avatarUrls":{"48x48":"https://issues.apache.org/jira/secure/useravatar?avatarId=10452","24x24":"https://issues.apache.org/jira/secure/useravatar?size=small&avatarId=10452","16x16":"https://issues.apache.org/jira/secure/useravatar?size=xsmall&avatarId=10452","32x32":"https://issues.apache.org/jira/secure/useravatar?size=medium&avatarId=10452"},"displayName":"Michael McCandless","active":true},"created":"2009-01-23T20:34:03.007+0000","updated":"2009-01-23T20:34:03.007+0000"}]},"votes":{"self":"https://issues.apache.org/jira/rest/api/2/issue/LUCENE-1527/votes","votes":0,"hasVoted":false},"worklog":{"startAt":0,"maxResults":20,"total":0,"worklogs":[]},"customfield_12311820":"0|i04wfr:"}}